conrad_relaycard/__init__.py
conrad_relaycard/card.py
conrad_relaycard/cli.py
conrad_relaycard/constants.py
conrad_relaycard/exceptions.py
conrad_relaycard/frame.py
conrad_relaycard/state.py
conrad_relaycard-0.1.dist-info/LICENSE.rst
conrad_relaycard-0.1.dist-info/METADATA
conrad_relaycard-0.1.dist-info/WHEEL
conrad_relaycard-0.1.dist-info/entry_points.txt
conrad_relaycard-0.1.dist-info/top_level.txt
conrad_relaycard-0.1.dist-info/RECORD
