Metadata-Version: 2.1
Name: conrad-relaycard
Version: 0.1
Summary: Library and commandline tool to control Conrad relay cards.
Home-page: https://github.com/stephrdev/conrad-relaycard/
Author: Stephan Jaekel
Author-email: steph@rdev.info
Classifier: Development Status :: 4 - Beta
Classifier: Environment :: Console
Classifier: Intended Audience :: Developers
Classifier: License :: OSI Approved :: BSD License
Classifier: Operating System :: OS Independent
Classifier: Programming Language :: Python
Requires-Python: >=3.6
License-File: LICENSE.rst
Requires-Dist: pyserial
